boggler/__init__.py
boggler/__main__.py
boggler/board_randomizer.py
boggler/boards/b1.csv
boggler/boards/b10.csv
boggler/boards/b2.csv
boggler/boards/b3.csv
boggler/boards/b4.csv
boggler/boards/b5.csv
boggler/boards/b6.csv
boggler/boards/b7.csv
boggler/boards/b8.csv
boggler/boards/b9.csv
boggler/boggler_utils.py
boggler/c/.gdb_history
boggler/c/Makefile
boggler/c/board.h
boggler/c/boggler.c
boggler/c/tree.h
boggler/dice/4x4_classic.csv
boggler/dice/4x4_new.csv
boggler/dice/5x5_big.csv
boggler/dice/6x6_super_big.csv
boggler/dice/9x9.csv
boggler/filter_prefix.sh
boggler/split_wordlist_en.sh
boggler/wordlists/dwyl/words__.txt
boggler/wordlists/dwyl/words_a.txt
boggler/wordlists/dwyl/words_alpha.txt
boggler/wordlists/dwyl/words_b.txt
boggler/wordlists/dwyl/words_c.txt
boggler/wordlists/dwyl/words_d.txt
boggler/wordlists/dwyl/words_e.txt
boggler/wordlists/dwyl/words_f.txt
boggler/wordlists/dwyl/words_g.txt
boggler/wordlists/dwyl/words_h.txt
boggler/wordlists/dwyl/words_i.txt
boggler/wordlists/dwyl/words_j.txt
boggler/wordlists/dwyl/words_k.txt
boggler/wordlists/dwyl/words_l.txt
boggler/wordlists/dwyl/words_m.txt
boggler/wordlists/dwyl/words_n.txt
boggler/wordlists/dwyl/words_o.txt
boggler/wordlists/dwyl/words_p.txt
boggler/wordlists/dwyl/words_q.txt
boggler/wordlists/dwyl/words_r.txt
boggler/wordlists/dwyl/words_s.txt
boggler/wordlists/dwyl/words_t.txt
boggler/wordlists/dwyl/words_u.txt
boggler/wordlists/dwyl/words_v.txt
boggler/wordlists/dwyl/words_w.txt
boggler/wordlists/dwyl/words_x.txt
boggler/wordlists/dwyl/words_y.txt
boggler/wordlists/dwyl/words_z.txt
boggler/wordlists/scrabble_2019/words__.txt
boggler/wordlists/scrabble_2019/words_a.txt
boggler/wordlists/scrabble_2019/words_alpha.txt
boggler/wordlists/scrabble_2019/words_b.txt
boggler/wordlists/scrabble_2019/words_c.txt
boggler/wordlists/scrabble_2019/words_d.txt
boggler/wordlists/scrabble_2019/words_e.txt
boggler/wordlists/scrabble_2019/words_f.txt
boggler/wordlists/scrabble_2019/words_g.txt
boggler-2.0.4.dist-info/LICENSE
boggler-2.0.4.dist-info/METADATA
boggler-2.0.4.dist-info/WHEEL
boggler-2.0.4.dist-info/entry_points.txt
boggler-2.0.4.dist-info/RECORD
