Metadata-Version: 2.1
Name: boggler
Version: 2.0.4
Summary: Utilities for solving the Boggle word game.
License: LICENSE
Author: Cameron Blankenbuehler
Author-email: cameron.blankenbuehler@gmail.com
Requires-Python: >=3.8,<4.0
Classifier: License :: OSI Approved :: MIT License
Classifier: License :: Other/Proprietary License
Classifier: Operating System :: POSIX :: Linux
Classifier: Programming Language :: Python :: 3
Classifier: Programming Language :: Python :: 3.8
Classifier: Programming Language :: Python :: 3.9
Classifier: Programming Language :: Python :: 3.10
Classifier: Programming Language :: Python :: 3.11
Classifier: Programming Language :: Python :: 3.12
Requires-Dist: rich (>=13.4.1,<14.0.0)
